[
  {
    "name": "嘉泷汇",
    "district": "浦东新区",
    "address": "浦东新区 嘉泷汇",
    "triggeredAt": "2021-01",
    "triggeredAtPrecision": "month",
    "sourceTitle": "用户整理-2021触发积分楼盘",
    "sourceUrl": "https://github.com/tianmagongyue/buy-house"
  },
  {
    "name": "尚海湾豪庭",
    "district": "徐汇区",
    "address": "徐汇区 尚海湾豪庭",
    "triggeredAt": "2021-01",
    "triggeredAtPrecision": "month",
    "sourceTitle": "用户整理-2021触发积分楼盘",
    "sourceUrl": "https://github.com/tianmagongyue/buy-house"
  },
  {
    "name": "星河湾花园三期",
    "district": "闵行区",
    "address": "闵行区 星河湾花园三期",
    "triggeredAt": "2021-01",
    "triggeredAtPrecision": "month",
    "sourceTitle": "用户整理-2021触发积分楼盘",
    "sourceUrl": "https://github.com/tianmagongyue/buy-house"
  },
  {
    "name": "招商悦庭（虹桥公馆二期）",
    "district": "青浦区",
    "address": "青浦区 招商悦庭（虹桥公馆二期）",
    "triggeredAt": "2021-01",
    "triggeredAtPrecision": "month",
    "sourceTitle": "用户整理-2021触发积分楼盘",
    "sourceUrl": "https://github.com/tianmagongyue/buy-house"
  },
  {
    "name": "泗水和鸣",
    "district": "松江区",
    "address": "松江区 泗水和鸣",
    "triggeredAt": "2021-01",
    "triggeredAtPrecision": "month",
    "sourceTitle": "用户整理-2021触发积分楼盘",
    "sourceUrl": "https://github.com/tianmagongyue/buy-house"
  },
  {
    "name": "金地褐石苑（金地丰盛道）",
    "district": "松江区",
    "address": "松江区 金地褐石苑（金地丰盛道）",
    "triggeredAt": "2021-01",
    "triggeredAtPrecision": "month",
    "sourceTitle": "用户整理-2021触发积分楼盘",
    "sourceUrl": "https://github.com/tianmagongyue/buy-house"
  },
  {
    "name": "南翔秀海纳名邸（海伦堡）",
    "district": "嘉定区",
    "address": "嘉定区 南翔秀海纳名邸（海伦堡）",
    "triggeredAt": "2021-01",
    "triggeredAtPrecision": "month",
    "sourceTitle": "用户整理-2021触发积分楼盘",
    "sourceUrl": "https://github.com/tianmagongyue/buy-house"
  },
  {
    "name": "万达观湖轩",
    "district": "临港新片区",
    "address": "临港新片区 万达观湖轩",
    "triggeredAt": "2021-01",
    "triggeredAtPrecision": "month",
    "sourceTitle": "用户整理-2021触发积分楼盘",
    "sourceUrl": "https://github.com/tianmagongyue/buy-house"
  }
]
